crengine/__init__.py
crengine/__main__.py
crengine/bellsound.py
crengine/crelib.py
crengine/easter.py
crengine/engine.py
crengine/htmldoc.py
crengine/postscript.py
crengine/ringing.py
crengine/rowfmt.py
crengine/rowset.py
crengine/svg.py
crengine/CRE/demo/8spliced.cre
crengine/CRE/demo/angelus.cre
crengine/CRE/demo/april-day.cre
crengine/CRE/demo/grandsire120.cre
crengine/CRE/demo/oranges.cre
crengine/CRE/demo/plainbob5.cre
crengine/CRE/demo/stclement.cre
crengine/CRE/demo/wedding-changes.cre
crengine/CRE/demo/westminster.cre
crengine/CRE/demo/xmas.cre
crengine/CRE/library/readme.txt
crengine/CRE/methods/plain.csv
crengine/CRE/methods/principle.csv
crengine/CRE/methods/teaching.csv
crengine/CRE/methods/trebledodging.csv
crengine/CRE/methods/user.csv
crengine/CRE/methods/variation.csv
crengine/CRE/towers/bellmap.csv
crengine/CRE/towers/tower.csv
crengine/CRE/towers/St_Michael/1.wav
crengine/CRE/towers/St_Michael/2.wav
crengine/CRE/towers/St_Michael/3.wav
crengine/CRE/towers/St_Michael/4.wav
crengine/CRE/towers/St_Michael/5.wav
crengine/CRE/towers/St_Michael/6.wav
crengine/CRE/towers/St_Wilfrid/0.wav
crengine/CRE/towers/St_Wilfrid/1.wav
crengine/CRE/towers/St_Wilfrid/2.wav
crengine/CRE/towers/St_Wilfrid/3.wav
crengine/CRE/towers/St_Wilfrid/4.wav
crengine/CRE/towers/St_Wilfrid/5.wav
crengine/CRE/towers/St_Wilfrid/6.wav
crengine/CRE/towers/St_Wilfrid/7.wav
crengine/CRE/towers/St_Wilfrid/8.wav
crengine/CRE/towers/St_Wilfrid/9.wav
crengine/CRE/towers/St_Wilfrid/E.wav
crengine/CRE/towers/St_Wilfrid/T.wav
crengine/CRE/towers/St_Wilfrid/W.wav
crengine/CRE/towers/St_Wilfrid/X.wav
crengine/help/bellview.html
crengine/help/block.html
crengine/help/chime.html
crengine/help/comment.html
crengine/help/echo.html
crengine/help/exit.html
crengine/help/help.txt
crengine/help/history.html
crengine/help/library.html
crengine/help/licence.txt
crengine/help/method.html
crengine/help/objects.html
crengine/help/output.html
crengine/help/placenotation.html
crengine/help/print.html
crengine-3.2.1.dist-info/LICENSE
crengine-3.2.1.dist-info/METADATA
crengine-3.2.1.dist-info/WHEEL
crengine-3.2.1.dist-info/top_level.txt
crengine-3.2.1.dist-info/RECORD
