Metadata-Version: 2.1
Name: crengine
Version: 3.2.1
Summary: The Change Ringing Engine
Home-page: https://harrogatebellringers.org/bellview
Author: Jonathan Wilson
Author-email: stwilfridsbells@gmail.com
License: UNKNOWN
Platform: UNKNOWN
Classifier: Programming Language :: Python :: 3
Classifier: License :: OSI Approved :: MIT License
Classifier: Operating System :: OS Independent
Requires-Python: >=2.7, !=3.0.*, !=3.1.*, !=3.2.*, !=3.3.*, <4
